{"authorDailyContributionsMap":{"jwdavis0200":[{"date":"2022-09-28","commitResults":[{"hash":"7cdb52dbfeda2fa637f8e1d3bdb31dc1acc65aed","messageTitle":"Update Developer Guide","messageBody":"","fileTypesAndContributionMap":{"docs":{"insertions":51,"deletions":9}}}]}],"cfyjoanna":[{"date":"2022-09-26","commitResults":[{"hash":"0b5f04b30228ec88cbe0e129958a68ce83bab9ff","messageTitle":"Updated PPP name","messageBody":"","fileTypesAndContributionMap":{"docs":{"insertions":5,"deletions":5}}},{"hash":"604b653604e75ecdc1fa43ad5400161fd78ca012","messageTitle":"Add skeletal PPP","messageBody":"","fileTypesAndContributionMap":{"docs":{"insertions":11,"deletions":37}}}]},{"date":"2022-09-27","commitResults":[{"hash":"c8de00e9aa317dbaf01d304f4d64eba725a4b99e","messageTitle":"Revert \"Add skeletal PPP\"","messageBody":"This reverts commit 604b653604e75ecdc1fa43ad5400161fd78ca012.\n","fileTypesAndContributionMap":{"docs":{"insertions":37,"deletions":11}}},{"hash":"344ced8f318dd919ee5db0c5684e8c5120cf3517","messageTitle":"Revert \"Updated PPP name\"","messageBody":"This reverts commit 0b5f04b30228ec88cbe0e129958a68ce83bab9ff.\n","fileTypesAndContributionMap":{"docs":{"insertions":5,"deletions":5}}},{"hash":"60e6488d8a9c19e841150b462ae7ddf80445d944","messageTitle":"Add PPP","messageBody":"","fileTypesAndContributionMap":{"docs":{"insertions":20,"deletions":0}}},{"hash":"c7dbbf3332d6a18196c7e45d1d70fe20ed11e866","messageTitle":"Add AboutUs description","messageBody":"","fileTypesAndContributionMap":{"docs":{"insertions":5,"deletions":5}}},{"hash":"20c00a9fe34d8d4931d4f8bed72e771b0191a97c","messageTitle":"Fix grammar","messageBody":"","fileTypesAndContributionMap":{"docs":{"insertions":1,"deletions":1}}}]},{"date":"2022-09-28","commitResults":[{"hash":"e1ad9bac83dca270026b93040510b87ec6534893","messageTitle":"Update DeveloperGuide","messageBody":"","fileTypesAndContributionMap":{"docs":{"insertions":34,"deletions":5}}}]}],"AshiqurRah":[{"date":"2022-09-28","commitResults":[{"hash":"64ca4abd5ca2f495e80f9e186cd2c4d0d99eb92d","messageTitle":"Add SkeletalPPP and Image","messageBody":"","fileTypesAndContributionMap":{"docs":{"insertions":26,"deletions":0}}}]}],"phyliciachristel":[{"date":"2022-09-27","commitResults":[{"hash":"86b2acaea3fb98476d2a99a3d63c0931326fb11e","messageTitle":"Add skeletal PPP","messageBody":"","fileTypesAndContributionMap":{"docs":{"insertions":29,"deletions":0}}},{"hash":"e924225b97d6f1a5a80a98699d0bf0ae21104881","messageTitle":"Revert \"Add skeletal PPP\"","messageBody":"","fileTypesAndContributionMap":{"docs":{"insertions":0,"deletions":29}}},{"hash":"f4a1d9123680dfd92e8534e3340aece40edf2147","messageTitle":"Add Skeleton PPP","messageBody":"","fileTypesAndContributionMap":{"docs":{"insertions":27,"deletions":0}}}]},{"date":"2022-09-28","commitResults":[{"hash":"82a5d6b00481d6543f4cb7914fa2ef580a1804ed","messageTitle":"Update AboutUs and add image","messageBody":"","fileTypesAndContributionMap":{"docs":{"insertions":26,"deletions":27}}},{"hash":"245d35298614baba6d05512ed88ddefe5056d485","messageTitle":"Fix CI checks","messageBody":"","fileTypesAndContributionMap":{"docs":{"insertions":2,"deletions":2}}}]}],"farisanadia":[{"date":"2022-09-28","commitResults":[{"hash":"e9dc416e19ac1240e29677bb323204762998c552","messageTitle":"updated User Guide","messageBody":"","fileTypesAndContributionMap":{"docs":{"insertions":42,"deletions":30}}},{"hash":"6fbb0f77f8e7352e82714436c3d2cab812678ee4","messageTitle":"added ppp and image","messageBody":"","fileTypesAndContributionMap":{"docs":{"insertions":31,"deletions":0}}},{"hash":"cd8098a44de2ebb9525174962ab047c248888c65","messageTitle":"no message","messageBody":"","fileTypesAndContributionMap":{"docs":{"insertions":1,"deletions":1}}},{"hash":"6092349b44849f349d9360a779e3390bf1ac0b43","messageTitle":"no message","messageBody":"","fileTypesAndContributionMap":{"docs":{"insertions":1,"deletions":1}}},{"hash":"703ace244475292f71a3c2f534735bee27e25057","messageTitle":"fixed java CI errors","messageBody":"","fileTypesAndContributionMap":{"docs":{"insertions":1,"deletions":1}}}]}]},"authorFileTypeContributionMap":{"jwdavis0200":{"docs":51,"functional-code":0,"test-code":0},"cfyjoanna":{"docs":57,"functional-code":0,"test-code":0},"AshiqurRah":{"docs":26,"functional-code":0,"test-code":0},"phyliciachristel":{"docs":49,"functional-code":0,"test-code":0},"farisanadia":{"docs":73,"functional-code":0,"test-code":0}},"authorContributionVariance":{"jwdavis0200":255.62132,"cfyjoanna":791.929,"AshiqurRah":48.0,"phyliciachristel":686.37866,"farisanadia":843.62134},"authorDisplayNameMap":{"jwdavis0200":"CS2103T-W09-4 JOHA..AVIS","cfyjoanna":"CS2103T-W09-4 CHAN..ANNA","AshiqurRah":"CS2103T-W09-4 ASHI..AMED","phyliciachristel":"CS2103T-W09-4 PHYL.. LIM","farisanadia":"CS2103T-W09-4 FARI..ALEK"}}
