{"authorDailyContributionsMap":{"gunbux":[],"limweijun":[{"date":"2022-09-16","commitResults":[{"hash":"f67072de4b1eb1921e337e9b2b5f020d118ee976","messageTitle":"Dummy commit","messageBody":"","fileTypesAndContributionMap":{"functional-code":{"insertions":0,"deletions":1}}},{"hash":"7ba5f4f2720966981778dbd63a6359febdc951bd","messageTitle":"Update index.md","messageBody":"","fileTypesAndContributionMap":{"docs":{"insertions":1,"deletions":1}}}]}],"yeojunjie":[],"tensaida":[],"LuYiting0913":[]},"authorFileTypeContributionMap":{"gunbux":{"docs":0,"functional-code":0,"test-code":0},"limweijun":{"docs":1,"functional-code":0,"test-code":0},"yeojunjie":{"docs":0,"functional-code":0,"test-code":0},"tensaida":{"docs":0,"functional-code":0,"test-code":0},"LuYiting0913":{"docs":0,"functional-code":0,"test-code":0}},"authorContributionVariance":{"gunbux":0.0,"limweijun":0.0,"yeojunjie":0.0,"tensaida":0.0,"LuYiting0913":0.0},"authorDisplayNameMap":{"gunbux":"CS2103T-T13-1 LAM ..N YU","limweijun":"CS2103T-T13-1 LIM .. JUN","yeojunjie":"CS2103T-T13-1 YEO .. JIE","tensaida":"CS2103T-T13-1 BAG ..UMAR","LuYiting0913":"CS2103T-T13-1 LU Y..TING"}}
