{"authorDailyContributionsMap":{"Puakii":[],"desmondyst":[],"Marcusgwj":[],"leeianee":[],"nerbnerb":[]},"authorFileTypeContributionMap":{"Puakii":{"docs":0,"functional-code":0,"test-code":0},"desmondyst":{"docs":0,"functional-code":0,"test-code":0},"Marcusgwj":{"docs":0,"functional-code":0,"test-code":0},"leeianee":{"docs":0,"functional-code":0,"test-code":0},"nerbnerb":{"docs":0,"functional-code":0,"test-code":0}},"authorContributionVariance":{"Puakii":0.0,"desmondyst":0.0,"Marcusgwj":0.0,"leeianee":0.0,"nerbnerb":0.0},"authorDisplayNameMap":{"Puakii":"CS2103T-T14-1 TEE ..TENG","desmondyst":"CS2103T-T14-1 DESM..TIAN","Marcusgwj":"CS2103T-T14-1 MARC.. JIE","leeianee":"CS2103T-T14-1 LEE ..N EE","nerbnerb":"CS2103T-T14-1 TAN ..NDAN"}}
