{"authorDailyContributionsMap":{"Puakii":[{"date":"2022-09-28","commitResults":[{"hash":"562f2d30d2c49f7d79fef759ec05d240432e5db9","messageTitle":"Update AboutUs to include personal details","messageBody":"","fileTypesAndContributionMap":{"docs":{"insertions":3,"deletions":3}}},{"hash":"195b08401c7537f36be34d8c4e27f2b8e480dcd7","messageTitle":"Update Quick Start section in User Guide","messageBody":"","fileTypesAndContributionMap":{"docs":{"insertions":22,"deletions":10}}},{"hash":"20a76015d720c25f81631179e6bbd5dc30018754","messageTitle":"Add Project Portfolio Page","messageBody":"","fileTypesAndContributionMap":{"docs":{"insertions":24,"deletions":0}}}]},{"date":"2022-09-29","commitResults":[{"hash":"958892155424b1b8c31126a24c3c107c126f403d","messageTitle":"Update User Guide","messageBody":"","fileTypesAndContributionMap":{"docs":{"insertions":19,"deletions":3}}},{"hash":"954749443e5c71606c79f0b4913057f6ff008b28","messageTitle":"Update Developer Guide","messageBody":"","fileTypesAndContributionMap":{"docs":{"insertions":1,"deletions":13}}},{"hash":"8a5b57300eb280193488416e981ae75115a0f030","messageTitle":"Update Developer Guide","messageBody":"","fileTypesAndContributionMap":{"docs":{"insertions":3,"deletions":3}}}]}],"desmondyst":[{"date":"2022-09-28","commitResults":[{"hash":"cc01577861fe71f3a9b2fa481a6b1265c02522db","messageTitle":"Update AboutUs","messageBody":"","fileTypesAndContributionMap":{"docs":{"insertions":6,"deletions":6}}},{"hash":"2b4e50aaeb28741c70725fcb2530a92c7a134909","messageTitle":"Update portfolio page","messageBody":"","fileTypesAndContributionMap":{"docs":{"insertions":25,"deletions":0}}}]},{"date":"2022-09-29","commitResults":[{"hash":"ed854f502c057ba0d4e3e93f64b3051247e19a3f","messageTitle":"Update UserGuide.md for mark function","messageBody":"","fileTypesAndContributionMap":{"docs":{"insertions":16,"deletions":11}}},{"hash":"af856546e74e18727627dbe6a87a584aee4a9259","messageTitle":"Add use cases in DG","messageBody":"","fileTypesAndContributionMap":{"docs":{"insertions":76,"deletions":12}}}]}],"Marcusgwj":[{"date":"2022-09-28","commitResults":[{"hash":"91d2d353d23fe06a9a46b46a2942731ab428c816","messageTitle":"Update AboutUs","messageBody":"","fileTypesAndContributionMap":{"docs":{"insertions":5,"deletions":5}}},{"hash":"91bcf96822148951bf46c679ebe27548a4497cd5","messageTitle":"Update naming of images","messageBody":"","fileTypesAndContributionMap":{"docs":{"insertions":4,"deletions":4}}},{"hash":"382ff3ebcb84837540236e223de0195430028af1","messageTitle":"Update ReadMe","messageBody":"","fileTypesAndContributionMap":{"docs":{"insertions":9,"deletions":12}}},{"hash":"3f72dbe6a46c334746ed40d7d7eb4a43366ead4d","messageTitle":"Update portfolio","messageBody":"","fileTypesAndContributionMap":{"docs":{"insertions":24,"deletions":0}}}]},{"date":"2022-09-29","commitResults":[{"hash":"294c965cdac347e853b21c5aa33d91a928224ddc","messageTitle":"Update UserGuide.md with filter function","messageBody":"","fileTypesAndContributionMap":{"docs":{"insertions":13,"deletions":76}}},{"hash":"f6a28d35b1ccad63672b6dce4c5c095f89195607","messageTitle":"Update User Guide","messageBody":"","fileTypesAndContributionMap":{"docs":{"insertions":8,"deletions":4}}},{"hash":"66b300d64147421d717571f01c56c202c7c4c8bd","messageTitle":"Update User Guide","messageBody":"","fileTypesAndContributionMap":{"docs":{"insertions":0,"deletions":1}}}]}],"leeianee":[{"date":"2022-09-28","commitResults":[{"hash":"640fd6f8109ee09da7db33c61793f05d5ae67526","messageTitle":"Update AboutUs.md","messageBody":"","fileTypesAndContributionMap":{"docs":{"insertions":5,"deletions":5}}},{"hash":"8c30a63c8a46631054ab5aaa51ce8cf93859cd3c","messageTitle":"Update AboutUs.md","messageBody":"","fileTypesAndContributionMap":{"docs":{"insertions":2,"deletions":2}}},{"hash":"42b509bb03f9ecc2a037925ff829f04d289e4f33","messageTitle":"Add skeletal PPP","messageBody":"","fileTypesAndContributionMap":{"docs":{"insertions":24,"deletions":46}}},{"hash":"69859e6dd609f03534ed469ad9f06be6e6086172","messageTitle":"Add newline at EOF","messageBody":"","fileTypesAndContributionMap":{"docs":{"insertions":1,"deletions":1}}},{"hash":"aef6b435f9e304f2bb152379527119e7cb0501e2","messageTitle":"Update target user profile, value proposition and user stories in DG","messageBody":"","fileTypesAndContributionMap":{"docs":{"insertions":10,"deletions":10}}},{"hash":"caead1880610d85db25c2a0377fa3d45ac9a69fb","messageTitle":"Add RepoSense link to portfolio page","messageBody":"","fileTypesAndContributionMap":{"docs":{"insertions":1,"deletions":1}}}]},{"date":"2022-09-29","commitResults":[{"hash":"977891b517499dd52e108d437eab7dd2c755a012","messageTitle":"Update UserGuide.md with list and delete functions","messageBody":"","fileTypesAndContributionMap":{"docs":{"insertions":11,"deletions":13}}}]}],"nerbnerb":[{"date":"2022-09-28","commitResults":[{"hash":"b12a21f67bf9db6c47ad44efead60135ae2e9c09","messageTitle":"Update `AboutUs` page","messageBody":"","fileTypesAndContributionMap":{"docs":{"insertions":6,"deletions":6}}},{"hash":"23537445cf8bf7358cb4469dabb1a1edf254f564","messageTitle":"Update name in `AboutUs` page","messageBody":"","fileTypesAndContributionMap":{"docs":{"insertions":1,"deletions":1}}},{"hash":"d6daae188425ca8a4f4ab049262cd770acb2751f","messageTitle":"Update portfolio page","messageBody":"","fileTypesAndContributionMap":{"docs":{"insertions":24,"deletions":0}}},{"hash":"889caacc32e0ae52f2b9f66bb0c09c5e3fb2745c","messageTitle":"Add new line at EOF","messageBody":"","fileTypesAndContributionMap":{"docs":{"insertions":1,"deletions":1}}},{"hash":"1176b63620eb31af58e983836a1996e4cc20b9cb","messageTitle":"Update `UserGuide.md` with add function","messageBody":"","fileTypesAndContributionMap":{"docs":{"insertions":7,"deletions":44}}}]}]},"authorFileTypeContributionMap":{"Puakii":{"docs":63,"functional-code":0,"test-code":0},"desmondyst":{"docs":95,"functional-code":0,"test-code":0},"Marcusgwj":{"docs":54,"functional-code":0,"test-code":0},"leeianee":{"docs":47,"functional-code":0,"test-code":0},"nerbnerb":{"docs":37,"functional-code":0,"test-code":0}},"authorContributionVariance":{"Puakii":345.38776,"desmondyst":924.5511,"Marcusgwj":887.7398,"leeianee":785.3877,"nerbnerb":549.25},"authorDisplayNameMap":{"Puakii":"CS2103T-T14-1 TEE ..TENG","desmondyst":"CS2103T-T14-1 DESM..TIAN","Marcusgwj":"CS2103T-T14-1 MARC.. JIE","leeianee":"CS2103T-T14-1 LEE ..N EE","nerbnerb":"CS2103T-T14-1 TAN ..NDAN"}}
